snt/__init__.py
snt/ExampleAgent.py
snt-0.0.1.dev1.dist-info/METADATA
snt-0.0.1.dev1.dist-info/WHEEL
snt-0.0.1.dev1.dist-info/RECORD
