Metadata-Version: 2.3
Name: snt
Version: 0.0.1.dev1
Summary: A HTTP1.1/2 compliant package
License: Apache-2.0
Author: Jacob Stewart
Author-email: jacob@swarmauri.com
Requires-Python: >=3.10,<3.13
Classifier: License :: OSI Approved :: Apache Software License
Classifier: Programming Language :: Python :: 3.10
Classifier: Programming Language :: Python :: 3.11
Classifier: Programming Language :: Python :: 3.12
